_chonk_version.py
chonk/__init__.py
chonk/__main__.py
chonk/filter.py
chonk/main.py
chonk/py.typed
chonk/utilities.py
chonk-0.2.4.dist-info/METADATA
chonk-0.2.4.dist-info/WHEEL
chonk-0.2.4.dist-info/entry_points.txt
chonk-0.2.4.dist-info/licenses/LICENSE
chonk-0.2.4.dist-info/RECORD
