Metadata-Version: 2.4
Name: chonk
Version: 0.2.4
Summary: codebase consolidation tool
Project-URL: Changelog, https://github.com/OLILHR/chonk/releases
Project-URL: Homepage, https://github.com/OLILHR/chonk
Author: OLILHR
License:                     GNU GENERAL PUBLIC LICENSE
License-File: LICENSE
Classifier: Development Status :: 4 - Beta
Classifier: Environment :: Console
Classifier: Intended Audience :: Developers
Classifier: License :: OSI Approved :: GNU General Public License v3 (GPLv3)
Classifier: Operating System :: OS Independent
Classifier: Programming Language :: Python
Classifier: Programming Language :: Python :: 3 :: Only
Classifier: Programming Language :: Python :: 3.12
Classifier: Topic :: Software Development :: Libraries :: Python Modules
Requires-Python: >=3.11
Requires-Dist: click>=8.1.7
Requires-Dist: prompt-toolkit>=3.0.47
Requires-Dist: tiktoken>=0.7.0
Requires-Dist: tqdm>=4.66.5
Requires-Dist: types-tqdm>=4.66.0
Provides-Extra: coverage
Requires-Dist: coverage==7.6.12; extra == 'coverage'
Provides-Extra: dev
Requires-Dist: pip-tools; extra == 'dev'
Provides-Extra: formatting
Requires-Dist: black==25.1.0; extra == 'formatting'
Requires-Dist: isort==6.0.1; extra == 'formatting'
Provides-Extra: linting
Requires-Dist: pylint==3.3.4; extra == 'linting'
Provides-Extra: packaging
Requires-Dist: build==1.2.2.post1; extra == 'packaging'
Requires-Dist: twine==6.1.0; extra == 'packaging'
Provides-Extra: spellchecking
Requires-Dist: codespell==2.4.1; extra == 'spellchecking'
Provides-Extra: testing
Requires-Dist: pytest==8.3.5; extra == 'testing'
Provides-Extra: typechecking
Requires-Dist: mypy==1.15.0; extra == 'typechecking'
